playground_pypi_package_e/__init__.py
playground_pypi_package_e-0.1.5.dist-info/METADATA
playground_pypi_package_e-0.1.5.dist-info/WHEEL
playground_pypi_package_e-0.1.5.dist-info/top_level.txt
playground_pypi_package_e-0.1.5.dist-info/RECORD
